plover_casecat_dictionary.py
plover_casecat_dictionary-0.1.3.dist-info/METADATA
plover_casecat_dictionary-0.1.3.dist-info/RECORD
plover_casecat_dictionary-0.1.3.dist-info/WHEEL
plover_casecat_dictionary-0.1.3.dist-info/entry_points.txt
plover_casecat_dictionary-0.1.3.dist-info/top_level.txt
plover_casecat_dictionary-0.1.3.dist-info/zip-safe
