Metadata-Version: 2.1
Name: plover-casecat-dictionary
Version: 0.1.3
Summary: CaseCat dictionary file support for Plover
Home-page: https://github.com/marnanel/plover_casecat_dictionary
Author: Marnanel Thurman
Author-email: marnanel@thurman.org.uk
License: GNU General Public License v2 or later (GPLv2+)
Keywords: plover plover_plugin
Platform: UNKNOWN
Classifier: Development Status :: 4 - Beta
Classifier: Environment :: Plugins
Classifier: Intended Audience :: End Users/Desktop
Classifier: License :: OSI Approved :: GNU General Public License v2 or later (GPLv2+)
Classifier: Operating System :: OS Independent
Classifier: Programming Language :: Python :: 3
Classifier: Programming Language :: Python :: 3.4
Classifier: Programming Language :: Python :: 3.5
Requires-Dist: plover (>=4.0.0.dev1)
